{"cameraMode":{"drawMode":0,"name":"Shaded","section":"Shading Mode"},"sceneLighting":true,"audioPlay":false,"sceneViewState":{"showFog":true,"showMaterialUpdate":false,"showSkybox":true,"showFlares":true,"showImageEffects":true,"showParticleSystems":true},"in2DMode":false,"pivot":{"x":39.555381774902347,"y":-20.001296997070314,"z":35.60404968261719},"rotation":{"x":0.5154218673706055,"y":-0.0012853313237428666,"z":0.0007732187514193356,"w":0.8569356203079224},"size":47.521522521972659,"orthographic":false}